obiba_agate/__init__.py
obiba_agate/auth_management/__init__.py
obiba_agate/auth_management/application.py
obiba_agate/auth_management/group.py
obiba_agate/auth_management/user.py
obiba_agate/console.py
obiba_agate/core.py
obiba_agate/rest.py
obiba_agate-3.1.0.dist-info/METADATA
obiba_agate-3.1.0.dist-info/WHEEL
obiba_agate-3.1.0.dist-info/entry_points.txt
obiba_agate-3.1.0.dist-info/licenses/LICENSE.txt
obiba_agate-3.1.0.dist-info/RECORD
