Metadata-Version: 2.4
Name: obiba-agate
Version: 3.1.0
Summary: OBiBa/Agate python client.
License: GPL-v3
License-File: LICENSE.txt
Author: Yannick Marcon
Author-email: yannick.marcon@obiba.org
Requires-Python: >=3.7,<4.0
Classifier: License :: Other/Proprietary License
Classifier: Programming Language :: Python :: 3
Classifier: Programming Language :: Python :: 3.7
Classifier: Programming Language :: Python :: 3.8
Classifier: Programming Language :: Python :: 3.9
Classifier: Programming Language :: Python :: 3.10
Classifier: Programming Language :: Python :: 3.11
Classifier: Programming Language :: Python :: 3.12
Classifier: Programming Language :: Python :: 3.13
Classifier: Programming Language :: Python :: 3.14
Requires-Dist: requests (>=2.31.0,<3.0.0)
Requires-Dist: urllib3 (==1.26.19)
